chulleeTest/test1.py
chulleeTest/test2.py
chulleeTest-0.0.0.2.dist-info/METADATA
chulleeTest-0.0.0.2.dist-info/WHEEL
chulleeTest-0.0.0.2.dist-info/top_level.txt
chulleeTest-0.0.0.2.dist-info/RECORD
