Metadata-Version: 2.1
Name: chulleeTest
Version: 0.0.0.2
Summary: My First Test Package
Home-page: https://blog.naver.com/bjy1530
Author: Chullee Kang
Author-email: freshday77@naver.com
License: MIT
Platform: UNKNOWN
Requires-Python: >=3
